ems/__init__.py
ems/ems.py
ems/receiver.py
ems/utils.py
openbaton_ems-1.2.2.data/scripts/add-upstart-ems
openbaton_ems-1.2.2.dist-info/METADATA
openbaton_ems-1.2.2.dist-info/RECORD
openbaton_ems-1.2.2.dist-info/WHEEL
openbaton_ems-1.2.2.dist-info/entry_points.txt
openbaton_ems-1.2.2.dist-info/top_level.txt
