Metadata-Version: 2.1
Name: openbaton-ems
Version: 1.2.2
Summary: Openbaton generic EMS
Home-page: http://openbaton.github.io/
Author: Openbaton
Author-email: dev@openbaton.org
License: Apache 2.0
Keywords: python ems vnfm openbaton open baton
Platform: UNKNOWN
Classifier: Development Status :: 4 - Beta
Classifier: Intended Audience :: Developers
Classifier: Topic :: Software Development
Classifier: License :: OSI Approved :: Apache Software License
Requires-Dist: pika (<=0.13.1)
Requires-Dist: gitpython
Requires-Dist: pyyaml
